{
 "issue": "1.1", 
 "tracks": [
  {
   "duration": "10", 
   "message-colour": "white", 
   "message-font": "Helvetica 20 bold", 
   "text": "You have successfuly triggered a show off a PIR\n\nThis show plays a few example tracks then waits for the PIR trigger.\n\nA more realistic example might play a single audio track or a video.\n", 
   "title": "Welcome", 
   "track-ref": "", 
   "type": "message"
  }, 
  {
   "duration": "5", 
   "location": "+/media/sarename.gif", 
   "title": "Sarename", 
   "track-ref": "", 
   "track-text": "", 
   "track-text-colour": "", 
   "track-text-font": "", 
   "track-text-x": "0", 
   "track-text-y": "0", 
   "transition": "cut", 
   "type": "image"
  }, 
  {
   "duration": "5", 
   "message-colour": "red", 
   "message-font": "Helvetica 30 bold", 
   "text": "That's it, its a one shot\n", 
   "title": "Bye", 
   "track-ref": "", 
   "type": "message"
  }
 ]
}